multimelt/T_S_profile_functions.py
multimelt/__init__.py
multimelt/box_functions.py
multimelt/constants.py
multimelt/create_isf_mask_functions.py
multimelt/deepmelt_functions.py
multimelt/melt_functions.py
multimelt/plume_functions.py
multimelt/useful_functions.py
multimelt-0.5.dist-info/LICENSE
multimelt-0.5.dist-info/METADATA
multimelt-0.5.dist-info/WHEEL
multimelt-0.5.dist-info/top_level.txt
multimelt-0.5.dist-info/RECORD
