Metadata-Version: 2.1
Name: multimelt
Version: 0.5
Summary: Regroupment of the main existing ice shelf basal melt parameterisations
Home-page: https://github.com/ClimateClara/multimelt
Author: Clara Burgard
Author-email: clara.burgard@locean.ipsl.fr
License: GPL-3.0
Project-URL: Source, https://github.com/ClimateClara/multimelt
Project-URL: Tracker, https://github.com/ClimateClara/multimelt/issues
Keywords: earth-sciences climate-modeling ice-sheet antarctica oceanography
Classifier: Development Status :: 4 - Beta
Classifier: Intended Audience :: Science/Research
Classifier: License :: OSI Approved :: GNU General Public License v3 (GPLv3)
Classifier: Operating System :: OS Independent
Classifier: Programming Language :: Python :: 3 :: Only
Requires-Python: >=3.5
License-File: LICENSE
Requires-Dist: numpy
Requires-Dist: xarray
Requires-Dist: pandas
Requires-Dist: tqdm
Requires-Dist: scipy
Requires-Dist: connected-components-3d
Requires-Dist: gsw
Requires-Dist: pyproj
Requires-Dist: dask
Requires-Dist: tensorflow
Provides-Extra: docs
Requires-Dist: sphinxcontrib.bibtex; extra == "docs"
Provides-Extra: extras
Requires-Dist: scipy; extra == "extras"
Requires-Dist: nlopt; extra == "extras"
Requires-Dist: mpi4py; extra == "extras"
Requires-Dist: petsc; extra == "extras"
Requires-Dist: petsc4py; extra == "extras"
